sentenceslug/__init__.py
sentenceslug/sentenceslug.py
sentenceslug/wordlists.py
sentenceslug-1.1.dist-info/LICENSE.txt
sentenceslug-1.1.dist-info/METADATA
sentenceslug-1.1.dist-info/WHEEL
sentenceslug-1.1.dist-info/top_level.txt
sentenceslug-1.1.dist-info/RECORD
