Metadata-Version: 2.1
Name: sentenceslug
Version: 1.1
Summary: Generate random slugs using basic sentence structure
Home-page: https://github.com/jef79m/sentenceslug
Author: jef79m
Author-email: jeff@fuzzknuckle.com
License: UNKNOWN
Keywords: random,slug,sentence
Platform: UNKNOWN
Classifier: Programming Language :: Python :: 3
Classifier: Operating System :: OS Independent
